[
  {
    "beginRow": null,
    "endRow": null,
    "curPage": null,
    "pageRow": null,
    "totalCount": 19,
    "rowNum": 1,
    "selectedCount": 19,
    "subwayId": "1063",
    "subwayNm": "\uacbd\uc758\uc911\uc559\uc120",
    "statnId": "1063075324",
    "statnNm": "\ubc31\ub9c8",
    "trainNo": "5098",
    "lastRecptnDt": "20201001",
    "recptnDt": "2020-10-01 17:00:31",
    "updnLine": "1",
    "statnTid": "1063075137",
    "statnTnm": "\uc6a9\ubb38",
    "trainSttus": "1",
    "directAt": "0",
    "lstcarAt": "0"
  },
  {
    "beginRow": null,
    "endRow": null,
    "curPage": null,
    "pageRow": null,
    "totalCount": 19,
    "rowNum": 2,
    "selectedCount": 19,
    "subwayId": "1063",
    "subwayNm": "\uacbd\uc758\uc911\uc559\uc120",
    "statnId": "1063075326",
    "statnNm": "\uc77c\uc0b0",
    "trainNo": "5083",
    "lastRecptnDt": "20201001",
    "recptnDt": "2020-10-01 17:00:42",
    "updnLine": "0",
    "statnTid": "1063075335",
    "statnTnm": "\ubb38\uc0b0",
    "trainSttus": "0",
    "directAt": "0",
    "lstcarAt": "0"
  },
  {
    "beginRow": null,
    "endRow": null,
    "curPage": null,
    "pageRow": null,
    "totalCount": 19,
    "rowNum": 3,
    "selectedCount": 19,
    "subwayId": "1063",
    "subwayNm": "\uacbd\uc758\uc911\uc559\uc120",
    "statnId": "1063075329",
    "statnNm": "\uc6b4\uc815",
    "trainNo": "5100",
    "lastRecptnDt": "20201001",
    "recptnDt": "2020-10-01 17:00:43",
    "updnLine": "1",
    "statnTid": "1063075128",
    "statnTnm": "\ud314\ub2f9",
    "trainSttus": "1",
    "directAt": "0",
    "lstcarAt": "0"
  },
  {
    "beginRow": null,
    "endRow": null,
    "curPage": null,
    "pageRow": null,
    "totalCount": 19,
    "rowNum": 4,
    "selectedCount": 19,
    "subwayId": "1063",
    "subwayNm": "\uacbd\uc758\uc911\uc559\uc120",
    "statnId": "1063075335",
    "statnNm": "\ubb38\uc0b0",
    "trainNo": "5104",
    "lastRecptnDt": "20201001",
    "recptnDt": "2020-10-01 16:57:05",
    "updnLine": "1",
    "statnTid": "1063075126",
    "statnTnm": "\ub355\uc18c",
    "trainSttus": "1",
    "directAt": "0",
    "lstcarAt": "0"
  },
  {
    "beginRow": null,
    "endRow": null,
    "curPage": null,
    "pageRow": null,
    "totalCount": 19,
    "rowNum": 5,
    "selectedCount": 19,
    "subwayId": "1063",
    "subwayNm": "\uacbd\uc758\uc911\uc559\uc120",
    "statnId": "1063075313",
    "statnNm": "\uc11c\uac15\ub300",
    "trainNo": "5087",
    "lastRecptnDt": "20201001",
    "recptnDt": "2020-10-01 17:00:32",
    "updnLine": "0",
    "statnTid": "1063075335",
    "statnTnm": "\ubb38\uc0b0",
    "trainSttus": "0",
    "directAt": "0",
    "lstcarAt": "0"
  },
  {
    "beginRow": null,
    "endRow": null,
    "curPage": null,
    "pageRow": null,
    "totalCount": 19,
    "rowNum": 6,
    "selectedCount": 19,
    "subwayId": "1063",
    "subwayNm": "\uacbd\uc758\uc911\uc559\uc120",
    "statnId": "1063075110",
    "statnNm": "\uc6a9\uc0b0",
    "trainNo": "5094",
    "lastRecptnDt": "20201001",
    "recptnDt": "2020-10-01 17:00:03",
    "updnLine": "1",
    "statnTid": "1063075138",
    "statnTnm": "\uc9c0\ud3c9",
    "trainSttus": "0",
    "directAt": "0",
    "lstcarAt": "0"
  },
  {
    "beginRow": null,
    "endRow": null,
    "curPage": null,
    "pageRow": null,
    "totalCount": 19,
    "rowNum": 7,
    "selectedCount": 19,
    "subwayId": "1063",
    "subwayNm": "\uacbd\uc758\uc911\uc559\uc120",
    "statnId": "1063075322",
    "statnNm": "\ub300\uace1",
    "trainNo": "2224",
    "lastRecptnDt": "20201001",
    "recptnDt": "2020-10-01 16:58:30",
    "updnLine": "1",
    "statnTid": "1063080313",
    "statnTnm": "\uc11c\uc6b8",
    "trainSttus": "1",
    "directAt": "0",
    "lstcarAt": "0"
  },
  {
    "beginRow": null,
    "endRow": null,
    "curPage": null,
    "pageRow": null,
    "totalCount": 19,
    "rowNum": 8,
    "selectedCount": 19,
    "subwayId": "1063",
    "subwayNm": "\uacbd\uc758\uc911\uc559\uc120",
    "statnId": "1063075113",
    "statnNm": "\ud55c\ub0a8",
    "trainNo": "5089",
    "lastRecptnDt": "20201001",
    "recptnDt": "2020-10-01 17:00:05",
    "updnLine": "0",
    "statnTid": "1063075335",
    "statnTnm": "\ubb38\uc0b0",
    "trainSttus": "1",
    "directAt": "0",
    "lstcarAt": "0"
  },
  {
    "beginRow": null,
    "endRow": null,
    "curPage": null,
    "pageRow": null,
    "totalCount": 19,
    "rowNum": 9,
    "selectedCount": 19,
    "subwayId": "1063",
    "subwayNm": "\uacbd\uc758\uc911\uc559\uc120",
    "statnId": "1063075115",
    "statnNm": "\uc751\ubd09",
    "trainNo": "5092",
    "lastRecptnDt": "20201001",
    "recptnDt": "2020-10-01 17:00:30",
    "updnLine": "1",
    "statnTid": "1063075126",
    "statnTnm": "\ub355\uc18c",
    "trainSttus": "1",
    "directAt": "0",
    "lstcarAt": "0"
  },
  {
    "beginRow": null,
    "endRow": null,
    "curPage": null,
    "pageRow": null,
    "totalCount": 19,
    "rowNum": 10,
    "selectedCount": 19,
    "subwayId": "1063",
    "subwayNm": "\uacbd\uc758\uc911\uc559\uc120",
    "statnId": "1063075117",
    "statnNm": "\uccad\ub7c9\ub9ac",
    "trainNo": "5091",
    "lastRecptnDt": "20201001",
    "recptnDt": "2020-10-01 16:59:51",
    "updnLine": "0",
    "statnTid": "1063075335",
    "statnTnm": "\ubb38\uc0b0",
    "trainSttus": "1",
    "directAt": "0",
    "lstcarAt": "0"
  },
  {
    "beginRow": null,
    "endRow": null,
    "curPage": null,
    "pageRow": null,
    "totalCount": 19,
    "rowNum": 11,
    "selectedCount": 19,
    "subwayId": "1063",
    "subwayNm": "\uacbd\uc758\uc911\uc559\uc120",
    "statnId": "1063075118",
    "statnNm": "\ud68c\uae30",
    "trainNo": "5090",
    "lastRecptnDt": "20201001",
    "recptnDt": "2020-10-01 17:00:38",
    "updnLine": "1",
    "statnTid": "1063075137",
    "statnTnm": "\uc6a9\ubb38",
    "trainSttus": "0",
    "directAt": "0",
    "lstcarAt": "0"
  },
  {
    "beginRow": null,
    "endRow": null,
    "curPage": null,
    "pageRow": null,
    "totalCount": 19,
    "rowNum": 12,
    "selectedCount": 19,
    "subwayId": "1063",
    "subwayNm": "\uacbd\uc758\uc911\uc559\uc120",
    "statnId": "1063075124",
    "statnNm": "\ub3c4\ub18d",
    "trainNo": "5088",
    "lastRecptnDt": "20201001",
    "recptnDt": "2020-10-01 16:59:55",
    "updnLine": "1",
    "statnTid": "1063075126",
    "statnTnm": "\ub355\uc18c",
    "trainSttus": "0",
    "directAt": "0",
    "lstcarAt": "0"
  },
  {
    "beginRow": null,
    "endRow": null,
    "curPage": null,
    "pageRow": null,
    "totalCount": 19,
    "rowNum": 13,
    "selectedCount": 19,
    "subwayId": "1063",
    "subwayNm": "\uacbd\uc758\uc911\uc559\uc120",
    "statnId": "1063075124",
    "statnNm": "\ub3c4\ub18d",
    "trainNo": "5093",
    "lastRecptnDt": "20201001",
    "recptnDt": "2020-10-01 16:59:53",
    "updnLine": "0",
    "statnTid": "1063075335",
    "statnTnm": "\ubb38\uc0b0",
    "trainSttus": "0",
    "directAt": "0",
    "lstcarAt": "0"
  },
  {
    "beginRow": null,
    "endRow": null,
    "curPage": null,
    "pageRow": null,
    "totalCount": 19,
    "rowNum": 14,
    "selectedCount": 19,
    "subwayId": "1063",
    "subwayNm": "\uacbd\uc758\uc911\uc559\uc120",
    "statnId": "1063075126",
    "statnNm": "\ub355\uc18c",
    "trainNo": "5086",
    "lastRecptnDt": "20201001",
    "recptnDt": "2020-10-01 17:00:23",
    "updnLine": "1",
    "statnTid": "1063075137",
    "statnTnm": "\uc6a9\ubb38",
    "trainSttus": "0",
    "directAt": "0",
    "lstcarAt": "0"
  },
  {
    "beginRow": null,
    "endRow": null,
    "curPage": null,
    "pageRow": null,
    "totalCount": 19,
    "rowNum": 15,
    "selectedCount": 19,
    "subwayId": "1063",
    "subwayNm": "\uacbd\uc758\uc911\uc559\uc120",
    "statnId": "1063075131",
    "statnNm": "\uc2e0\uc6d0",
    "trainNo": "5097",
    "lastRecptnDt": "20201001",
    "recptnDt": "2020-10-01 17:00:01",
    "updnLine": "0",
    "statnTid": "1063075335",
    "statnTnm": "\ubb38\uc0b0",
    "trainSttus": "1",
    "directAt": "0",
    "lstcarAt": "0"
  },
  {
    "beginRow": null,
    "endRow": null,
    "curPage": null,
    "pageRow": null,
    "totalCount": 19,
    "rowNum": 16,
    "selectedCount": 19,
    "subwayId": "1063",
    "subwayNm": "\uacbd\uc758\uc911\uc559\uc120",
    "statnId": "1063075135",
    "statnNm": "\uc591\ud3c9",
    "trainNo": "5082",
    "lastRecptnDt": "20201001",
    "recptnDt": "2020-10-01 16:59:45",
    "updnLine": "1",
    "statnTid": "1063075137",
    "statnTnm": "\uc6a9\ubb38",
    "trainSttus": "1",
    "directAt": "0",
    "lstcarAt": "0"
  },
  {
    "beginRow": null,
    "endRow": null,
    "curPage": null,
    "pageRow": null,
    "totalCount": 19,
    "rowNum": 17,
    "selectedCount": 19,
    "subwayId": "1063",
    "subwayNm": "\uacbd\uc758\uc911\uc559\uc120",
    "statnId": "1063080312",
    "statnNm": "\uc2e0\ucd0c(\uacbd\uc758.\uc911\uc559\uc120)",
    "trainNo": "2222",
    "lastRecptnDt": "20201001",
    "recptnDt": "2020-10-01 16:59:36",
    "updnLine": "1",
    "statnTid": "1063080313",
    "statnTnm": "\uc11c\uc6b8",
    "trainSttus": "1",
    "directAt": "0",
    "lstcarAt": "0"
  },
  {
    "beginRow": null,
    "endRow": null,
    "curPage": null,
    "pageRow": null,
    "totalCount": 19,
    "rowNum": 18,
    "selectedCount": 19,
    "subwayId": "1063",
    "subwayNm": "\uacbd\uc758\uc911\uc559\uc120",
    "statnId": "1063075317",
    "statnNm": "\uc218\uc0c9",
    "trainNo": "5085",
    "lastRecptnDt": "20201001",
    "recptnDt": "2020-10-01 16:58:45",
    "updnLine": "0",
    "statnTid": "1063075335",
    "statnTnm": "\ubb38\uc0b0",
    "trainSttus": "1",
    "directAt": "0",
    "lstcarAt": "0"
  },
  {
    "beginRow": null,
    "endRow": null,
    "curPage": null,
    "pageRow": null,
    "totalCount": 19,
    "rowNum": 19,
    "selectedCount": 19,
    "subwayId": "1063",
    "subwayNm": "\uacbd\uc758\uc911\uc559\uc120",
    "statnId": "1063075318",
    "statnNm": "\ud654\uc804",
    "trainNo": "5096",
    "lastRecptnDt": "20201001",
    "recptnDt": "2020-10-01 17:00:29",
    "updnLine": "1",
    "statnTid": "1063075126",
    "statnTnm": "\ub355\uc18c",
    "trainSttus": "0",
    "directAt": "0",
    "lstcarAt": "0"
  }
]